pastree/__init__.py
pastree/cli.py
tests/__init__.py
tests/test_pastree.py
pastree-0.1.3.dist-info/LICENSE
pastree-0.1.3.dist-info/METADATA
pastree-0.1.3.dist-info/WHEEL
pastree-0.1.3.dist-info/entry_points.txt
pastree-0.1.3.dist-info/top_level.txt
pastree-0.1.3.dist-info/RECORD
