Metadata-Version: 2.1
Name: pastree
Version: 0.1.3
Summary: Generate directory structures from tree-like input.
Home-page: https://github.com/xdotcommer/pastree
Author: Michael Cowden
Author-email: mike@novate.ai
Classifier: Programming Language :: Python :: 3
Classifier: License :: OSI Approved :: MIT License
Classifier: Operating System :: OS Independent
Requires-Python: >=3.7
License-File: LICENSE
